mandelbrot_benchmark/__init__.py
mandelbrot_benchmark/__main__.py
mandelbrot_benchmark/cli.py
mandelbrot_benchmark/plot.py
mandelbrot_benchmark/py.typed
mandelbrot_benchmark/backends/__init__.py
mandelbrot_benchmark/backends/jax.py
mandelbrot_benchmark/backends/numba.py
mandelbrot_benchmark/backends/taichi.py
mandelbrot_benchmark/backends/torch.py
mandelbrot_benchmark/backends/warp.py
mandelbrot_benchmark-1.1.4.dist-info/licenses/LICENSE
mandelbrot_benchmark-1.1.4.dist-info/METADATA
mandelbrot_benchmark-1.1.4.dist-info/WHEEL
mandelbrot_benchmark-1.1.4.dist-info/entry_points.txt
mandelbrot_benchmark-1.1.4.dist-info/top_level.txt
mandelbrot_benchmark-1.1.4.dist-info/RECORD
