Metadata-Version: 2.4
Name: mandelbrot-benchmark
Version: 1.1.4
Summary: Benchmark Numba, Taichi, Warp, CuPy Kernel, Triton using Mandelbrot set
Author-email: 34j <34j.95a2p@simplelogin.com>
License: MIT
Project-URL: Bug Tracker, https://github.com/34j/mandelbrot-benchmark/issues
Project-URL: Changelog, https://github.com/34j/mandelbrot-benchmark/blob/main/CHANGELOG.md
Project-URL: documentation, https://mandelbrot-benchmark.readthedocs.io
Project-URL: repository, https://github.com/34j/mandelbrot-benchmark
Classifier: Development Status :: 2 - Pre-Alpha
Classifier: Intended Audience :: Developers
Classifier: Natural Language :: English
Classifier: Operating System :: OS Independent
Classifier: Programming Language :: Python :: 3.10
Classifier: Programming Language :: Python :: 3.11
Classifier: Programming Language :: Python :: 3.12
Classifier: Programming Language :: Python :: 3.13
Classifier: Topic :: Software Development :: Libraries
Requires-Python: >=3.10
License-File: LICENSE
Requires-Dist: aquarel>=0.0.7
Requires-Dist: array-api-compat>=1.11.2
Requires-Dist: cm-time>=0.1.2
Requires-Dist: jax[cuda12]>=0.4.30
Requires-Dist: matplotlib>=3.9.4
Requires-Dist: numba>=0.60.0
Requires-Dist: numpy<=2.3.4
Requires-Dist: pandas>=2.3.1
Requires-Dist: pydlpack>=0.2.1
Requires-Dist: rich>=10
Requires-Dist: seaborn>=0.13.2
Requires-Dist: taichi>=1.7.4
Requires-Dist: torch>=2.8.0
Requires-Dist: tqdm>=4.67.1
Requires-Dist: typer<1,>=0.15
Requires-Dist: warp-lang>=1.8.1
Dynamic: license-file
